econlib/__init__.py
econlib/example_module.py
econlib/linearmodel.py
econlib/result.py
econlib/tool.py
econlib-0.0.3.dist-info/LICENSE
econlib-0.0.3.dist-info/METADATA
econlib-0.0.3.dist-info/WHEEL
econlib-0.0.3.dist-info/top_level.txt
econlib-0.0.3.dist-info/RECORD
